Workbook

Sheet Inputs
A1: ROI calculator, UC-01 freight document intelligence (fictional client)
A2: Change the yellow Base column. Low and high are the scenario bounds used in the business case.
A4: # | B4: Assumption | C4: Base | D4: Low | E4: High | F4: Unit | G4: Source | H4: Basis
A5: A01 | B5: Documents keyed per month | C5: 4000 | D5: 3600 | E5: 4400 | F5: documents | G5: measured | H5: Two-week mailbox count, September 2026, extrapolated.
A6: A02 | B6: Annual volume growth | C6: 0.04 | D6: 0.02 | E6: 0.06 | F6: % | G6: client plan | H6: CFO's 2027-2029 plan.
A7: A03 | B7: Minutes to key one document today | C7: 5.5 | D7: 4.5 | E7: 6.5 | F7: minutes | G7: measured | H7: Discovery time study, 60 documents, two clerks.
A8: A04 | B8: Minutes to review a flagged document | C8: 2.5 | D8: 2 | E8: 3.5 | F8: minutes | G8: estimate | H8: Clerk checks only the flagged fields; to be measured in the first production month.
A9: A05 | B9: Minutes per straight-through document (sample audit) | C9: 0.3 | D9: 0.2 | E9: 0.5 | F9: minutes | G9: design | H9: 5% random audit of straight-through documents at 6 minutes each.
A10: A06 | B10: Straight-through rate | C10: 0.7 | D10: 0.6364 | E10: 0.7567 | F10: % | G10: pilot | H10: Test set result; low and high are the 95% confidence interval.
A11: A07 | B11: Share of documents handled fully by hand | C11: 0.0455 | D11: 0.0455 | E11: 0.0455 | F11: % | G11: pilot | H11: Not freight documents or type unsure.
A12: A08 | B12: Loaded cost per clerk hour | C12: 34 | D12: 31 | E12: 37 | F12: EUR | G12: client finance | H12: EUR 52,000 loaded cost per clerk / 1,530 productive hours.
A13: A09 | B13: Loaded cost per clerk per year | C13: 52000 | D13: 52000 | E13: 52000 | F13: EUR | G13: client finance | H13: HR, 2026 salary scales plus employer costs.
A14: A10 | B14: Productive hours per FTE per year | C14: 1530 | D14: 1530 | E14: 1530 | F14: hours | G14: client finance | H14: HR.
A15: A11 | B15: Documents with a keying error today | C15: 0.021 | D15: 0.015 | E15: 0.028 | F15: % | G15: measured | H15: Time study: 60 documents double-checked.
A16: A12 | B16: Cost of one error that reaches operations | C16: 60 | D16: 35 | E16: 110 | F16: EUR | G16: estimate | H16: Operations and customs leads: rework, customs amendment, share of demurrage. Wide range on purpose.
... A28: A24 | B28: Discount rate | C28: 0.08 | D28: 0.08 | E28: 0.08 | F28: % | G28: client finance | H28: CFO's hurdle rate.
B30: Doc desk headcount (FTE) | C30: 11

Sheet Model
A1: Calculation (do not edit; change Inputs)
B3: Year 1 | C3: Year 2 | D3: Year 3
A4: Year | B4: 1 | C4: 2 | D4: 3
A5: Review rate | B5: =1-Inputs!$C$10-Inputs!$C$11
A6: Minutes per document after | B6: =Inputs!$C$10*Inputs!$C$9+B5*Inputs!$C$8+Inputs!$C$11*Inputs!$C$7
A7: Minutes saved per document | B7: =Inputs!$C$7-B6
A8: Error rate after | B8: =Inputs!$C$17+B5*Inputs!$C$15*Inputs!$C$18+Inputs!$C$11*Inputs!$C$15
A9: Model cost per document (EUR) | B9: =(Inputs!$C$21*Inputs!$C$23+Inputs!$C$22*Inputs!$C$24)/1000000*Inputs!$C$25
A10: Documents | B10: =12*Inputs!$C$5*(1+Inputs!$C$6)^(B4-1) | C10: =12*Inputs!$C$5*(1+Inputs!$C$6)^(C4-1) | D10: =12*Inputs!$C$5*(1+Inputs!$C$6)^(D4-1)
A11: Ramp | B11: =IF(B4=1,Inputs!$C$26,1) | C11: =IF(C4=1,Inputs!$C$26,1) | D11: =IF(D4=1,Inputs!$C$26,1)
A12: Clerk hours freed | B12: =B10*$B$7/60*B11 | C12: =C10*$B$7/60*C11 | D12: =D10*$B$7/60*D11
A13: FTE freed | B13: =B12/Inputs!$C$14 | C13: =C12/Inputs!$C$14 | D13: =D12/Inputs!$C$14
A14: Hires avoided (growth + leavers not replaced) | B14: =Inputs!$C$30*((1+Inputs!$C$6)^B4-1)+Inputs!$C$27*B4 | C14: =Inputs!$C$30*((1+Inputs!$C$6)^C4-1)+Inputs!$C$27*C4 | D14: =Inputs!$C$30*((1+Inputs!$C$6)^D4-1)+Inputs!$C$27*D4
A15: FTE leaving the cost base (cash view) | B15: =MIN(B13,B14) | C15: =MIN(C13,C14) | D15: =MIN(D13,D14)
A16: Errors avoided | B16: =B10*(Inputs!$C$15-$B$8)*B11 | C16: =C10*(Inputs!$C$15-$B$8)*C11 | D16: =D10*(Inputs!$C$15-$B$8)*D11
A17: Capacity value | B17: =B12*Inputs!$C$12 | C17: =C12*Inputs!$C$12 | D17: =D12*Inputs!$C$12
A18: Cash labour value | B18: =B15*Inputs!$C$13 | C18: =C15*Inputs!$C$13 | D18: =D15*Inputs!$C$13
A19: Error cost avoided | B19: =B16*Inputs!$C$16 | C19: =C16*Inputs!$C$16 | D19: =D16*Inputs!$C$16
A20: Run cost incl. model usage | B20: =Inputs!$C$20+B10*$B$9 | C20: =Inputs!$C$20+C10*$B$9 | D20: =Inputs!$C$20+D10*$B$9
A21: Net, capacity view | B21: =B17+B19-B20 | C21: =C17+C19-C20 | D21: =D17+D19-D20
A22: Net, cash view | B22: =B18+B19-B20 | C22: =C18+C19-C20 | D22: =D18+D19-D20
A24: One-off cost | B24: =Inputs!$C$19
A25: NPV, capacity view | B25: =-B24+NPV(Inputs!$C$28,B21:D21)
A26: NPV, cash view | B26: =-B24+NPV(Inputs!$C$28,B22:D22)
A27: 3-year ROI, cash view | B27: =(SUM(B22:D22)-B24)/B24
A29: Reference values from the Python model: NPV cash €188,729, NPV capacity €232,249. With the base inputs Excel shows the same, give or take rounding.
