Workbook

Sheet Scorecard
A1: AI readiness scorecard: Wendelkaai Logistics (fictional)
A2: Yellow cells are inputs (1-5). Gap and summary update automatically.
A4: # | B4: Dimension | C4: Question | D4: Today | E4: Target | F4: Gap | G4: Evidence
A5: S1 | B5: Strategy & leadership | C5: AI ambition is linked to named business goals | D5: 2 | E5: 4 | F5: =E5-D5 | G5: The board asked for 'an AI plan'; no goals or KPIs attached. The 2027 business plan names margin pressure and doc desk hiring problems, not AI.
A6: S2 | B6: Strategy & leadership | C6: An executive sponsor owns AI and has a budget | D6: 2 | E6: 4 | F6: =E6-D6 | G6: The CEO sponsors informally; no budget line. IT funds tool trials from its own budget.
A7: S3 | B7: Strategy & leadership | C7: AI initiatives are managed as one portfolio | D7: 1 | E7: 3 | F7: =E7-D7 | G7: Three unconnected experiments found (sales ChatGPT prompts, a customs Excel macro with an AI add-in, a warehouse vendor demo). Nobody had an overview.
A8: S4 | B8: Strategy & leadership | C8: Value is measured against a baseline | D8: 2 | E8: 4 | F8: =E8-D8 | G8: Doc desk volumes are counted per month; handling time and error rates were never measured before the discovery time study.
A9: S5 | B9: Strategy & leadership | C9: There is a view on partners and buy versus build | D9: 2 | E9: 3 | F9: =E9-D9 | G9: IT prefers the TMS vendor's roadmap; operations wants faster results. No criteria to decide.
A10: D1 | B10: Data foundations | C10: Data domains have named owners | D10: 1 | E10: 3 | F10: =E10-D10 | G10: Customer and location master data are edited by whoever needs a change. No owner for document data.
A11: D2 | B11: Data foundations | C11: Core master data is of usable quality | D11: 2 | E11: 3 | F11: =E11-D11 | G11: Sample of 200 customer records: 14% duplicates, 9% missing VAT or EORI.
A12: D3 | B12: Data foundations | C12: Documents are available digitally | D12: 3 | E12: 4 | F12: =E12-D12 | G12: 90% of documents arrive as PDF by e-mail; the rest is scanned at the desk. Archive in the TMS document store, 7 years.
A13: D4 | B13: Data foundations | C13: Labelled historical data exists to evaluate AI | D13: 1 | E13: 3 | F13: =E13-D13 | G13: None before the pilot. The pilot built the first labelled sets (2 x 220 documents).
A14: D5 | B14: Data foundations | C14: Core systems can be reached through APIs | D14: 2 | E14: 4 | F14: =E14-D14 | G14: The TMS has an import API for bookings, undocumented for documents; the ERP only exports files overnight.
A15: T1 | B15: Technology & tooling | C15: Cloud platform and identity are in place | D15: 3 | E15: 4 | F15: =E15-D15 | G15: Microsoft 365 and Entra ID for all staff; one Azure subscription used for backups.
A16: T2 | B16: Technology & tooling | C16: Staff have sanctioned AI tools | D16: 2 | E16: 4 | F16: =E16-D16 | G16: No approved tool; the staff survey shows 38% use public chatbots for work, including with customer data.
... A34: O5 | B34: Process & operations | C34: Teams improve their own work | D34: 3 | E34: 4 | F34: =E34-D34 | G34: Monthly operations meeting with improvement actions; strong pragmatism on the floor.

Sheet Summary
A1: Dimension | B1: Today | C1: Target | D1: Gap
A2: Strategy & leadership | B2: =ROUND(AVERAGEIF(Scorecard!$B$5:$B$34,A2,Scorecard!$D$5:$D$34),2) | C2: =ROUND(AVERAGEIF(Scorecard!$B$5:$B$34,A2,Scorecard!$E$5:$E$34),2) | D2: =C2-B2
A3: Data foundations | B3: =ROUND(AVERAGEIF(Scorecard!$B$5:$B$34,A3,Scorecard!$D$5:$D$34),2) | C3: =ROUND(AVERAGEIF(Scorecard!$B$5:$B$34,A3,Scorecard!$E$5:$E$34),2) | D3: =C3-B3
A4: Technology & tooling | B4: =ROUND(AVERAGEIF(Scorecard!$B$5:$B$34,A4,Scorecard!$D$5:$D$34),2) | C4: =ROUND(AVERAGEIF(Scorecard!$B$5:$B$34,A4,Scorecard!$E$5:$E$34),2) | D4: =C4-B4
A5: Governance, risk & compliance | B5: =ROUND(AVERAGEIF(Scorecard!$B$5:$B$34,A5,Scorecard!$D$5:$D$34),2) | C5: =ROUND(AVERAGEIF(Scorecard!$B$5:$B$34,A5,Scorecard!$E$5:$E$34),2) | D5: =C5-B5
A6: People & skills | B6: =ROUND(AVERAGEIF(Scorecard!$B$5:$B$34,A6,Scorecard!$D$5:$D$34),2) | C6: =ROUND(AVERAGEIF(Scorecard!$B$5:$B$34,A6,Scorecard!$E$5:$E$34),2) | D6: =C6-B6
A7: Process & operations | B7: =ROUND(AVERAGEIF(Scorecard!$B$5:$B$34,A7,Scorecard!$D$5:$D$34),2) | C7: =ROUND(AVERAGEIF(Scorecard!$B$5:$B$34,A7,Scorecard!$E$5:$E$34),2) | D7: =C7-B7
A8: Overall | B8: =ROUND(AVERAGE(B2:B7),2) | C8: =ROUND(AVERAGE(C2:C7),2) | D8: =C8-B8
